ou_print_pack_tools/__init__.py
ou_print_pack_tools/print_publication.py
ou_print_pack_tools/resources/OU-logo-36x28.png
ou_print_pack_tools/resources/OU-logo-53x42.png
ou_print_pack_tools/resources/OU-logo-83x65.png
ou_print_pack_tools/resources/OU_Compact_LOGO_BLUE_14mm.png
ou_print_pack_tools/resources/OU_Master_LOGO_BLACK_14mm.png
ou_print_pack_tools/resources/OU_Master_LOGO_BLACK_63mm.png
ou_print_pack_tools-0.0.7.dist-info/LICENSE
ou_print_pack_tools-0.0.7.dist-info/METADATA
ou_print_pack_tools-0.0.7.dist-info/WHEEL
ou_print_pack_tools-0.0.7.dist-info/entry_points.txt
ou_print_pack_tools-0.0.7.dist-info/RECORD
